odoo/addons/l10n_ru/README.rst
odoo/addons/l10n_ru/__init__.py
odoo/addons/l10n_ru/__manifest__.py
odoo/addons/l10n_ru/data/account.account.template.csv
odoo/addons/l10n_ru/data/account_chart.xml
odoo/addons/l10n_ru/data/account_chart_template.xml
odoo/addons/l10n_ru/data/account_chart_template.yml
odoo/addons/l10n_ru/data/account_tax_template.xml
odoo/addons/l10n_ru/i18n/l10n_ru.pot
odoo/addons/l10n_ru/readme/CONTRIBUTORS.rst
odoo/addons/l10n_ru/readme/DESCRIPTION.rst
odoo/addons/l10n_ru/static/description/account.png
odoo/addons/l10n_ru/static/description/icon.png
odoo/addons/l10n_ru/static/description/index.html
odoo11_addon_l10n_ru-11.0.0.0.1.99.dev2.dist-info/METADATA
odoo11_addon_l10n_ru-11.0.0.0.1.99.dev2.dist-info/WHEEL
odoo11_addon_l10n_ru-11.0.0.0.1.99.dev2.dist-info/top_level.txt
odoo11_addon_l10n_ru-11.0.0.0.1.99.dev2.dist-info/RECORD
