Metadata-Version: 2.1
Name: odoo11-addon-l10n-ru
Version: 11.0.0.0.1.99.dev2
Summary: Russia - Accounting
Home-page: https://github.com/OCA/l10n-russia
Author: CodUP, Odoo Community Association (OCA)
Author-email: support@odoo-community.org
License: AGPL-3
Platform: UNKNOWN
Classifier: Programming Language :: Python
Classifier: Framework :: Odoo
Classifier: Framework :: Odoo :: 11.0
Classifier: License :: OSI Approved :: GNU Affero General Public License v3
Requires-Python: >=2.7, !=3.0.*, !=3.1.*, !=3.2.*, !=3.3.*, !=3.4.*
Requires-Dist: odoo <11.1dev,>=11.0a
